Spotify247Listen/__init__.py
Spotify247Listen/simple.py
Spotify247Listen/core/__init__.py
Spotify247Listen/utils/__init__.py
Spotify247Listen/utils/helper_functions.py
Spotify247Listen-0.1.2.dist-info/LICENSE
Spotify247Listen-0.1.2.dist-info/METADATA
Spotify247Listen-0.1.2.dist-info/WHEEL
Spotify247Listen-0.1.2.dist-info/top_level.txt
Spotify247Listen-0.1.2.dist-info/RECORD
