Metadata-Version: 2.1
Name: Spotify247Listen
Version: 0.1.2
Summary: A simple python script that listens to a Spotify playlist 24/7
License: MIT License
Project-URL: Homepage, https://github.com/CodeByAidan/Spotify247Listen
Project-URL: Bug Reports, https://github.com/CodeByAidan/Spotify247Listen/issues
Project-URL: Source, https://github.com/CodeByAidan/Spotify247Listen/
Keywords: sample,setuptools,development
Classifier: Development Status :: 3 - Alpha
Classifier: Intended Audience :: Developers
Classifier: Topic :: Software Development :: Build Tools
Classifier: License :: OSI Approved :: MIT License
Classifier: Programming Language :: Python :: 3
Classifier: Programming Language :: Python :: 3.8
Classifier: Programming Language :: Python :: 3.9
Classifier: Programming Language :: Python :: 3.10
Classifier: Programming Language :: Python :: 3.11
Classifier: Programming Language :: Python :: 3.12
Classifier: Programming Language :: Python :: 3 :: Only
Requires-Python: >=3.8
License-File: LICENSE
Provides-Extra: dev
Requires-Dist: check-manifest ; extra == 'dev'
Provides-Extra: test
Requires-Dist: coverage ; extra == 'test'
